[
  {
    "name": "entity_ids",
    "type": "object({\n    instance_ids   = optional(list(string))\n    repository_ids = optional(list(string))\n  })",
    "description": "List of secure source manager instance or repository names",
    "default": "",
    "required": true
  },
  {
    "name": "mode",
    "type": "string",
    "description": "Mode for adding the IAM policies/bindings, additive and authoritative",
    "default": "\"additive\"",
    "required": false
  },
  {
    "name": "bindings",
    "type": "map(any)",
    "description": "Map of role (key) and list of members (value) to add the IAM policies/bindings",
    "default": "",
    "required": true
  },
  {
    "name": "location",
    "type": "string",
    "description": "The location for the secure source manager Instance",
    "default": "",
    "required": true
  },
  {
    "name": "project",
    "type": "string",
    "description": "Project to add the IAM policies/bindings",
    "default": "",
    "required": true
  }
]
